{
  "urls": {
    "https://www.facebook.com/groups/romaffitti/posts/1342922560832768/": {
      "reason": "AI_NOT_RELEVANT",
      "timestamp": "2025-09-07T20:28:24.725381"
    },
    "https://www.facebook.com/groups/1800846897105933/posts/2152209208636365/": {
      "reason": "AI_NOT_RELEVANT",
      "timestamp": "2025-09-07T20:29:02.341198"
    },
    "https://www.facebook.com/groups/1800846897105933/posts/2152203915303561/": {
      "reason": "AI_NOT_RELEVANT",
      "timestamp": "2025-09-07T20:29:02.343037"
    },
    "https://www.facebook.com/groups/1800846897105933/posts/2152202408637045/": {
      "reason": "AI_NOT_RELEVANT",
      "timestamp": "2025-09-07T20:29:38.709681"
    },
    "https://www.facebook.com/groups/1800846897105933/posts/2152118818645404/": {
      "reason": "AI_NOT_RELEVANT",
      "timestamp": "2025-09-07T20:29:38.711515"
    },
    "https://www.facebook.com/groups/633912783969846/posts/1714997602528020/": {
      "reason": "AI_NOT_RELEVANT",
      "timestamp": "2025-09-07T20:30:53.338721"
    },
    "https://www.facebook.com/groups/633912783969846/posts/1714992825861831/": {
      "reason": "AI_NOT_RELEVANT",
      "timestamp": "2025-09-07T20:30:53.340575"
    },
    "https://www.facebook.com/groups/633912783969846/posts/1714988465862267/": {
      "reason": "AI_NOT_RELEVANT",
      "timestamp": "2025-09-07T20:30:53.342417"
    },
    "https://www.facebook.com/groups/633912783969846/posts/1714981769196270/": {
      "reason": "AI_NOT_RELEVANT",
      "timestamp": "2025-09-07T20:31:29.463179"
    },
    "https://www.facebook.com/groups/romaffitti/posts/1342960340828990/": {
      "reason": "AI_NOT_RELEVANT",
      "timestamp": "2025-09-07T21:22:09.316934"
    },
    "https://www.facebook.com/groups/romaffitti/posts/1342952127496478/": {
      "reason": "AI_NOT_RELEVANT",
      "timestamp": "2025-09-07T21:22:09.318813"
    },
    "https://www.facebook.com/groups/1800846897105933/posts/2152255465298406/": {
      "reason": "AI_NOT_RELEVANT",
      "timestamp": "2025-09-07T21:22:48.968330"
    },
    "https://www.facebook.com/groups/1800846897105933/posts/2152254748631811/": {
      "reason": "AI_NOT_RELEVANT",
      "timestamp": "2025-09-07T21:22:48.970223"
    },
    "https://www.facebook.com/groups/1800846897105933/posts/2152252705298682/": {
      "reason": "AI_NOT_RELEVANT",
      "timestamp": "2025-09-07T21:23:26.029772"
    },
    "https://www.facebook.com/groups/1800846897105933/posts/2152251981965421/": {
      "reason": "AI_NOT_RELEVANT",
      "timestamp": "2025-09-07T21:23:26.031632"
    },
    "https://www.facebook.com/groups/affitti.stanze.studenti.roma/posts/2739393632926271/": {
      "reason": "AI_NOT_RELEVANT",
      "timestamp": "2025-09-07T21:24:03.518569"
    },
    "https://www.facebook.com/groups/affitti.stanze.studenti.roma/posts/2739389619593339/": {
      "reason": "AI_NOT_RELEVANT",
      "timestamp": "2025-09-07T21:24:03.520417"
    },
    "https://www.facebook.com/groups/affitti.stanze.studenti.roma/posts/2739369029595398/": {
      "reason": "AI_NOT_RELEVANT",
      "timestamp": "2025-09-07T21:24:03.522241"
    },
    "https://www.facebook.com/groups/affitti.stanze.studenti.roma/posts/2739325922933042/": {
      "reason": "AI_NOT_RELEVANT",
      "timestamp": "2025-09-07T21:24:42.005941"
    },
    "https://www.facebook.com/groups/affitti.stanze.studenti.roma/posts/2739321992933435/": {
      "reason": "AI_NOT_RELEVANT",
      "timestamp": "2025-09-07T21:25:21.565013"
    },
    "https://www.facebook.com/groups/affitti.stanze.studenti.roma/posts/2739315669600734/": {
      "reason": "AI_NOT_RELEVANT",
      "timestamp": "2025-09-07T21:25:21.567544"
    },
    "https://www.facebook.com/groups/AffittoCaseRoma/posts/31121473020830789/": {
      "reason": "AI_NOT_RELEVANT",
      "timestamp": "2025-09-07T21:26:34.989084"
    },
    "https://www.facebook.com/groups/633912783969846/posts/1715021889192258/": {
      "reason": "AI_NOT_RELEVANT",
      "timestamp": "2025-09-07T21:27:13.957438"
    },
    "https://www.facebook.com/groups/633912783969846/posts/1715020595859054/": {
      "reason": "AI_NOT_RELEVANT",
      "timestamp": "2025-09-07T21:27:13.959270"
    },
    "https://www.facebook.com/groups/1800846897105933/posts/2152287125295240/": {
      "reason": "AI_NOT_RELEVANT",
      "timestamp": "2025-09-07T22:24:24.008264"
    },
    "https://www.facebook.com/groups/1800846897105933/posts/2152286321961987/": {
      "reason": "AI_NOT_RELEVANT",
      "timestamp": "2025-09-07T22:24:24.010117"
    },
    "https://www.facebook.com/groups/affitti.stanze.studenti.roma/posts/2739305652935069/": {
      "reason": "AI_NOT_RELEVANT",
      "timestamp": "2025-09-07T22:25:00.810978"
    },
    "https://www.facebook.com/groups/AffittoCaseRoma/posts/31122471497397608/": {
      "reason": "AI_NOT_RELEVANT",
      "timestamp": "2025-09-07T22:25:39.516925"
    },
    "https://www.facebook.com/groups/633912783969846/posts/1715037945857319/": {
      "reason": "AI_NOT_RELEVANT",
      "timestamp": "2025-09-07T22:26:18.976605"
    },
    "https://www.facebook.com/groups/633912783969846/posts/1715032672524513/": {
      "reason": "AI_NOT_RELEVANT",
      "timestamp": "2025-09-07T22:26:18.978439"
    },
    "https://www.facebook.com/groups/romaffitti/posts/1343010497490641/": {
      "reason": "AI_NOT_RELEVANT",
      "timestamp": "2025-09-07T23:21:17.754892"
    },
    "https://www.facebook.com/groups/romaffitti/posts/1343004654157892/": {
      "reason": "AI_NOT_RELEVANT",
      "timestamp": "2025-09-07T23:21:17.756836"
    },
    "https://www.facebook.com/groups/1800846897105933/posts/2152317515292201/": {
      "reason": "AI_NOT_RELEVANT",
      "timestamp": "2025-09-07T23:22:43.071301"
    },
    "https://www.facebook.com/groups/1800846897105933/posts/2152314181959201/": {
      "reason": "AI_NOT_RELEVANT",
      "timestamp": "2025-09-07T23:22:43.073199"
    },
    "https://www.facebook.com/groups/1800846897105933/posts/2152310115292941/": {
      "reason": "AI_NOT_RELEVANT",
      "timestamp": "2025-09-07T23:22:43.075100"
    },
    "https://www.facebook.com/groups/1800846897105933/posts/2152309091959710/": {
      "reason": "AI_NOT_RELEVANT",
      "timestamp": "2025-09-07T23:23:18.100116"
    },
    "https://www.facebook.com/groups/affitti.stanze.studenti.roma/posts/2739423282923306/": {
      "reason": "AI_NOT_RELEVANT",
      "timestamp": "2025-09-07T23:23:55.028678"
    },
    "https://www.facebook.com/groups/633912783969846/posts/1715073145853799/": {
      "reason": "AI_NOT_RELEVANT",
      "timestamp": "2025-09-07T23:24:32.917041"
    },
    "https://www.facebook.com/groups/633912783969846/posts/1714761859218261/": {
      "reason": "AI_NOT_RELEVANT",
      "timestamp": "2025-09-07T23:24:32.918967"
    },
    "https://www.facebook.com/groups/244234206083096/posts/2186735661832931/": {
      "reason": "AI_NOT_RELEVANT",
      "timestamp": "2025-09-07T23:25:10.876329"
    },
    "https://www.facebook.com/groups/244234206083096/posts/2185105148662649/": {
      "reason": "AI_NOT_RELEVANT",
      "timestamp": "2025-09-07T23:25:10.878287"
    },
    "https://www.facebook.com/groups/romaffitti/posts/1343065464151811/": {
      "reason": "AI_NOT_RELEVANT",
      "timestamp": "2025-09-08T01:58:30.315093"
    },
    "https://www.facebook.com/groups/affitti.stanze.studenti.roma/posts/2739501489582152/": {
      "reason": "AI_NOT_RELEVANT",
      "timestamp": "2025-09-08T01:59:09.280537"
    },
    "https://www.facebook.com/groups/affitti.stanze.studenti.roma/posts/2739504969581804/": {
      "reason": "AI_NOT_RELEVANT",
      "timestamp": "2025-09-08T01:59:09.282370"
    },
    "https://www.facebook.com/groups/romaffitti/posts/1343180767473614/": {
      "reason": "AI_NOT_RELEVANT",
      "timestamp": "2025-09-08T05:24:42.063542"
    },
    "https://www.facebook.com/groups/romaffitti/posts/1343172507474440/": {
      "reason": "AI_NOT_RELEVANT",
      "timestamp": "2025-09-08T05:24:42.065359"
    },
    "https://www.facebook.com/groups/romaffitti/posts/1343134597478231/": {
      "reason": "AI_NOT_RELEVANT",
      "timestamp": "2025-09-08T05:24:42.067535"
    },
    "https://www.facebook.com/groups/633912783969846/posts/1715297129164734/": {
      "reason": "AI_NOT_RELEVANT",
      "timestamp": "2025-09-08T06:40:15.727541"
    },
    "https://www.facebook.com/groups/633912783969846/posts/1715295862498194/": {
      "reason": "AI_NOT_RELEVANT",
      "timestamp": "2025-09-08T06:40:15.729382"
    },
    "https://www.facebook.com/groups/633912783969846/posts/1715004502527330/": {
      "reason": "AI_NOT_RELEVANT",
      "timestamp": "2025-09-08T06:40:15.731335"
    },
    "https://www.facebook.com/groups/633912783969846/posts/1714888129205634/": {
      "reason": "AI_NOT_RELEVANT",
      "timestamp": "2025-09-08T06:40:50.258691"
    },
    "https://www.facebook.com/groups/244234206083096/posts/2186938675145963/": {
      "reason": "AI_NOT_RELEVANT",
      "timestamp": "2025-09-08T06:41:24.928697"
    },
    "https://www.facebook.com/groups/romaffitti/posts/1343242187467472/": {
      "reason": "AI_NOT_RELEVANT",
      "timestamp": "2025-09-08T07:28:39.787458"
    },
    "https://www.facebook.com/groups/romaffitti/posts/1343240954134262/": {
      "reason": "AI_NOT_RELEVANT",
      "timestamp": "2025-09-08T07:28:39.789404"
    },
    "https://www.facebook.com/groups/romaffitti/posts/1343236024134755/": {
      "reason": "AI_NOT_RELEVANT",
      "timestamp": "2025-09-08T07:28:39.791344"
    },
    "https://www.facebook.com/groups/romaffitti/posts/1343233740801650/": {
      "reason": "AI_NOT_RELEVANT",
      "timestamp": "2025-09-08T07:29:20.519449"
    },
    "https://www.facebook.com/groups/romaffitti/posts/1343227717468919/": {
      "reason": "AI_NOT_RELEVANT",
      "timestamp": "2025-09-08T07:29:20.522192"
    },
    "https://www.facebook.com/groups/romaffitti/posts/1343226697469021/": {
      "reason": "AI_NOT_RELEVANT",
      "timestamp": "2025-09-08T07:29:57.748037"
    },
    "https://www.facebook.com/groups/romaffitti/posts/1343220134136344/": {
      "reason": "AI_NOT_RELEVANT",
      "timestamp": "2025-09-08T07:29:57.749938"
    },
    "https://www.facebook.com/groups/1800846897105933/posts/2152563055267647/": {
      "reason": "AI_NOT_RELEVANT",
      "timestamp": "2025-09-08T07:30:38.835087"
    },
    "https://www.facebook.com/groups/1800846897105933/posts/2152557268601559/": {
      "reason": "AI_NOT_RELEVANT",
      "timestamp": "2025-09-08T07:30:38.837838"
    },
    "https://www.facebook.com/groups/affitti.stanze.studenti.roma/posts/2739747526224215/": {
      "reason": "AI_NOT_RELEVANT",
      "timestamp": "2025-09-08T07:31:49.602555"
    },
    "https://www.facebook.com/groups/romaffitti/posts/1343265420798482/": {
      "reason": "AI_NOT_RELEVANT",
      "timestamp": "2025-09-08T08:36:21.981389"
    },
    "https://www.facebook.com/groups/AffittoCaseRoma/posts/31128106496834108/": {
      "reason": "AI_NOT_RELEVANT",
      "timestamp": "2025-09-08T08:37:36.159174"
    },
    "https://www.facebook.com/groups/AffittoCaseRoma/posts/31127860433525381/": {
      "reason": "AI_NOT_RELEVANT",
      "timestamp": "2025-09-08T08:37:36.161043"
    },
    "https://www.facebook.com/groups/AffittoCaseRoma/posts/31127498516894906/": {
      "reason": "AI_NOT_RELEVANT",
      "timestamp": "2025-09-08T08:37:36.162962"
    },
    "https://www.facebook.com/groups/633912783969846/posts/1715323099162137/": {
      "reason": "AI_NOT_RELEVANT",
      "timestamp": "2025-09-08T08:39:05.356996"
    },
    "https://www.facebook.com/groups/633912783969846/posts/1715317889162658/": {
      "reason": "AI_NOT_RELEVANT",
      "timestamp": "2025-09-08T08:39:05.359766"
    },
    "https://www.facebook.com/groups/633912783969846/posts/1715299889164458/": {
      "reason": "AI_NOT_RELEVANT",
      "timestamp": "2025-09-08T08:39:47.866099"
    },
    "https://www.facebook.com/groups/633912783969846/posts/1714799459214501/": {
      "reason": "AI_NOT_RELEVANT",
      "timestamp": "2025-09-08T08:39:47.870716"
    },
    "https://www.facebook.com/groups/romaffitti/posts/1343306034127754/": {
      "reason": "AI_NOT_RELEVANT",
      "timestamp": "2025-09-08T09:33:31.843209"
    },
    "https://www.facebook.com/groups/1800846897105933/posts/2152556821934937/": {
      "reason": "AI_NOT_RELEVANT",
      "timestamp": "2025-09-08T09:34:06.380293"
    },
    "https://www.facebook.com/groups/633912783969846/posts/1715354915825622/": {
      "reason": "AI_NOT_RELEVANT",
      "timestamp": "2025-09-08T09:35:21.773281"
    },
    "https://www.facebook.com/groups/633912783969846/posts/1715354595825654/": {
      "reason": "AI_NOT_RELEVANT",
      "timestamp": "2025-09-08T09:35:21.776400"
    },
    "https://www.facebook.com/groups/633912783969846/posts/1715352259159221/": {
      "reason": "AI_NOT_RELEVANT",
      "timestamp": "2025-09-08T09:35:21.779367"
    },
    "https://www.facebook.com/groups/633912783969846/posts/1715337319160715/": {
      "reason": "AI_NOT_RELEVANT",
      "timestamp": "2025-09-08T09:35:59.734877"
    },
    "https://www.facebook.com/groups/633912783969846/posts/1715299075831206/": {
      "reason": "AI_NOT_RELEVANT",
      "timestamp": "2025-09-08T09:35:59.736735"
    },
    "https://www.facebook.com/groups/244234206083096/posts/2185454325294398/": {
      "reason": "AI_NOT_RELEVANT",
      "timestamp": "2025-09-08T09:36:41.070442"
    },
    "https://www.facebook.com/groups/244234206083096/posts/2185439875295843/": {
      "reason": "AI_NOT_RELEVANT",
      "timestamp": "2025-09-08T09:36:41.072397"
    },
    "https://www.facebook.com/groups/romaffitti/posts/1343338370791187/": {
      "reason": "AI_NOT_RELEVANT",
      "timestamp": "2025-09-08T10:29:59.027929"
    },
    "https://www.facebook.com/groups/romaffitti/posts/1343337444124613/": {
      "reason": "AI_NOT_RELEVANT",
      "timestamp": "2025-09-08T10:29:59.029903"
    },
    "https://www.facebook.com/groups/romaffitti/posts/1343336900791334/": {
      "reason": "AI_NOT_RELEVANT",
      "timestamp": "2025-09-08T10:30:44.542890"
    },
    "https://www.facebook.com/groups/romaffitti/posts/1343336614124696/": {
      "reason": "AI_NOT_RELEVANT",
      "timestamp": "2025-09-08T10:30:44.544749"
    },
    "https://www.facebook.com/groups/affitti.stanze.studenti.roma/posts/2739858032879831/": {
      "reason": "AI_NOT_RELEVANT",
      "timestamp": "2025-09-08T10:32:08.616822"
    },
    "https://www.facebook.com/groups/affitti.stanze.studenti.roma/posts/2739852929547008/": {
      "reason": "AI_NOT_RELEVANT",
      "timestamp": "2025-09-08T10:32:08.618748"
    },
    "https://www.facebook.com/groups/affitti.stanze.studenti.roma/posts/2739848756214092/": {
      "reason": "AI_NOT_RELEVANT",
      "timestamp": "2025-09-08T10:32:08.620663"
    },
    "https://www.facebook.com/groups/affitti.stanze.studenti.roma/posts/2739844706214497/": {
      "reason": "AI_NOT_RELEVANT",
      "timestamp": "2025-09-08T10:32:45.862380"
    },
    "https://www.facebook.com/groups/affitti.stanze.studenti.roma/posts/2739836339548667/": {
      "reason": "AI_NOT_RELEVANT",
      "timestamp": "2025-09-08T10:32:45.867137"
    },
    "https://www.facebook.com/groups/AffittoCaseRoma/posts/31129137433397681/": {
      "reason": "AI_NOT_RELEVANT",
      "timestamp": "2025-09-08T10:33:27.837347"
    },
    "https://www.facebook.com/groups/AffittoCaseRoma/posts/31128921513419273/": {
      "reason": "AI_NOT_RELEVANT",
      "timestamp": "2025-09-08T10:33:27.840205"
    },
    "https://www.facebook.com/groups/AffittoCaseRoma/posts/31128552943456130/": {
      "reason": "AI_NOT_RELEVANT",
      "timestamp": "2025-09-08T10:34:13.606725"
    },
    "https://www.facebook.com/groups/AffittoCaseRoma/posts/31128533456791412/": {
      "reason": "AI_NOT_RELEVANT",
      "timestamp": "2025-09-08T10:34:13.608601"
    },
    "https://www.facebook.com/groups/AffittoCaseRoma/posts/31128421960135895/": {
      "reason": "AI_NOT_RELEVANT",
      "timestamp": "2025-09-08T10:34:13.610457"
    },
    "https://www.facebook.com/groups/1800846897105933/posts/2152691335254819/": {
      "reason": "AI_NOT_RELEVANT",
      "timestamp": "2025-09-08T11:20:50.264063"
    },
    "https://www.facebook.com/groups/1800846897105933/posts/2152687141921905/": {
      "reason": "AI_NOT_RELEVANT",
      "timestamp": "2025-09-08T11:20:50.267631"
    },
    "https://www.facebook.com/groups/1800846897105933/posts/2152686765255276/": {
      "reason": "AI_NOT_RELEVANT",
      "timestamp": "2025-09-08T11:21:28.386711"
    },
    "https://www.facebook.com/groups/1800846897105933/posts/2152682498589036/": {
      "reason": "AI_NOT_RELEVANT",
      "timestamp": "2025-09-08T11:21:28.390647"
    },
    "https://www.facebook.com/groups/1800846897105933/posts/2152680858589200/": {
      "reason": "AI_NOT_RELEVANT",
      "timestamp": "2025-09-08T11:22:03.891849"
    },
    "https://www.facebook.com/groups/1800846897105933/posts/2152680791922540/": {
      "reason": "AI_NOT_RELEVANT",
      "timestamp": "2025-09-08T11:22:03.893715"
    },
    "https://www.facebook.com/groups/1800846897105933/posts/2152680451922574/": {
      "reason": "AI_NOT_RELEVANT",
      "timestamp": "2025-09-08T11:22:03.895721"
    },
    "https://www.facebook.com/groups/1800846897105933/posts/2152675665256386/": {
      "reason": "AI_NOT_RELEVANT",
      "timestamp": "2025-09-08T11:22:39.686258"
    },
    "https://www.facebook.com/groups/affitti.stanze.studenti.roma/posts/2739909009541400/": {
      "reason": "AI_NOT_RELEVANT",
      "timestamp": "2025-09-08T11:23:18.520710"
    },
    "https://www.facebook.com/groups/affitti.stanze.studenti.roma/posts/2739906039541697/": {
      "reason": "AI_NOT_RELEVANT",
      "timestamp": "2025-09-08T11:23:18.522614"
    },
    "https://www.facebook.com/groups/affitti.stanze.studenti.roma/posts/2739899932875641/": {
      "reason": "AI_NOT_RELEVANT",
      "timestamp": "2025-09-08T11:24:05.077645"
    },
    "https://www.facebook.com/groups/affitti.stanze.studenti.roma/posts/2739897566209211/": {
      "reason": "AI_NOT_RELEVANT",
      "timestamp": "2025-09-08T11:24:05.079632"
    },
    "https://www.facebook.com/groups/affitti.stanze.studenti.roma/posts/2739893292876305/": {
      "reason": "AI_NOT_RELEVANT",
      "timestamp": "2025-09-08T11:24:42.730764"
    },
    "https://www.facebook.com/groups/AffittoCaseRoma/posts/31129685743342850/": {
      "reason": "AI_NOT_RELEVANT",
      "timestamp": "2025-09-08T11:25:27.122657"
    },
    "https://www.facebook.com/groups/633912783969846/posts/1715418185819295/": {
      "reason": "AI_NOT_RELEVANT",
      "timestamp": "2025-09-08T11:26:11.686444"
    },
    "https://www.facebook.com/groups/633912783969846/posts/1715417925819321/": {
      "reason": "AI_NOT_RELEVANT",
      "timestamp": "2025-09-08T11:26:11.688311"
    },
    "https://www.facebook.com/groups/244234206083096/posts/2187100731796424/": {
      "reason": "AI_NOT_RELEVANT",
      "timestamp": "2025-09-08T11:27:03.084475"
    },
    "https://www.facebook.com/groups/244234206083096/posts/2187086101797887/": {
      "reason": "AI_NOT_RELEVANT",
      "timestamp": "2025-09-08T11:27:03.086410"
    },
    "https://www.facebook.com/groups/1800846897105933/posts/2152729705250982/": {
      "reason": "AI_NOT_RELEVANT",
      "timestamp": "2025-09-08T12:58:32.003002"
    },
    "https://www.facebook.com/groups/1800846897105933/posts/2152710845252868/": {
      "reason": "AI_NOT_RELEVANT",
      "timestamp": "2025-09-08T12:58:32.008121"
    },
    "https://www.facebook.com/groups/AffittoCaseRoma/posts/31130912499886841/": {
      "reason": "AI_NOT_RELEVANT",
      "timestamp": "2025-09-08T12:59:15.896374"
    },
    "https://www.facebook.com/groups/AffittoCaseRoma/posts/31130846599893431/": {
      "reason": "AI_NOT_RELEVANT",
      "timestamp": "2025-09-08T12:59:15.900457"
    },
    "https://www.facebook.com/groups/AffittoCaseRoma/posts/31130836339894457/": {
      "reason": "AI_NOT_RELEVANT",
      "timestamp": "2025-09-08T12:59:58.525567"
    },
    "https://www.facebook.com/groups/AffittoCaseRoma/posts/31130719953239429/": {
      "reason": "AI_NOT_RELEVANT",
      "timestamp": "2025-09-08T12:59:58.527875"
    },
    "https://www.facebook.com/groups/633912783969846/posts/1715485685812545/": {
      "reason": "AI_NOT_RELEVANT",
      "timestamp": "2025-09-08T13:01:27.162616"
    },
    "https://www.facebook.com/groups/633912783969846/posts/1715476372480143/": {
      "reason": "AI_NOT_RELEVANT",
      "timestamp": "2025-09-08T13:01:27.164932"
    },
    "https://www.facebook.com/groups/633912783969846/posts/1715470095814104/": {
      "reason": "AI_NOT_RELEVANT",
      "timestamp": "2025-09-08T13:01:27.166849"
    },
    "https://www.facebook.com/groups/633912783969846/posts/1715450649149382/": {
      "reason": "AI_NOT_RELEVANT",
      "timestamp": "2025-09-08T13:02:07.787065"
    },
    "https://www.facebook.com/groups/633912783969846/posts/1715442825816831/": {
      "reason": "AI_NOT_RELEVANT",
      "timestamp": "2025-09-08T13:02:49.968041"
    },
    "https://www.facebook.com/groups/633912783969846/posts/1715440652483715/": {
      "reason": "AI_NOT_RELEVANT",
      "timestamp": "2025-09-08T13:02:49.970516"
    },
    "https://www.facebook.com/groups/244234206083096/posts/2187158295124001/": {
      "reason": "AI_NOT_RELEVANT",
      "timestamp": "2025-09-08T13:04:03.212878"
    },
    "https://www.facebook.com/groups/244234206083096/posts/2187149968458167/": {
      "reason": "AI_NOT_RELEVANT",
      "timestamp": "2025-09-08T13:04:03.214951"
    },
    "https://www.facebook.com/groups/244234206083096/posts/2187146685125162/": {
      "reason": "AI_NOT_RELEVANT",
      "timestamp": "2025-09-08T13:04:43.886251"
    },
    "https://www.facebook.com/groups/244234206083096/posts/2187118158461348/": {
      "reason": "AI_NOT_RELEVANT",
      "timestamp": "2025-09-08T13:04:43.891954"
    },
    "https://www.facebook.com/groups/633912783969846/posts/1715523625808751/": {
      "reason": "AI_NOT_RELEVANT",
      "timestamp": "2025-09-08T14:27:23.277909"
    },
    "https://www.facebook.com/groups/633912783969846/posts/1715522099142237/": {
      "reason": "AI_NOT_RELEVANT",
      "timestamp": "2025-09-08T14:27:23.280092"
    },
    "https://www.facebook.com/groups/633912783969846/posts/1715517525809361/": {
      "reason": "AI_NOT_RELEVANT",
      "timestamp": "2025-09-08T14:27:23.282096"
    },
    "https://www.facebook.com/groups/633912783969846/posts/1715502045810909/": {
      "reason": "AI_NOT_RELEVANT",
      "timestamp": "2025-09-08T14:28:01.116345"
    },
    "https://www.facebook.com/groups/633912783969846/posts/1715497115811402/": {
      "reason": "AI_NOT_RELEVANT",
      "timestamp": "2025-09-08T14:28:01.118211"
    },
    "https://www.facebook.com/groups/633912783969846/posts/1715495049144942/": {
      "reason": "AI_NOT_RELEVANT",
      "timestamp": "2025-09-08T14:28:42.229172"
    },
    "https://www.facebook.com/groups/244234206083096/posts/2185621475277683/": {
      "reason": "AI_NOT_RELEVANT",
      "timestamp": "2025-09-08T14:29:26.924228"
    },
    "https://www.facebook.com/groups/244234206083096/posts/2185599521946545/": {
      "reason": "AI_NOT_RELEVANT",
      "timestamp": "2025-09-08T14:29:26.926243"
    },
    "https://www.facebook.com/groups/244234206083096/posts/2185575978615566/": {
      "reason": "AI_NOT_RELEVANT",
      "timestamp": "2025-09-08T14:29:26.928115"
    },
    "https://www.facebook.com/groups/romaffitti/posts/1343488640776160/": {
      "reason": "AI_NOT_RELEVANT",
      "timestamp": "2025-09-08T15:27:42.901169"
    },
    "https://www.facebook.com/groups/romaffitti/posts/1343477780777246/": {
      "reason": "AI_NOT_RELEVANT",
      "timestamp": "2025-09-08T15:27:42.903111"
    },
    "https://www.facebook.com/groups/romaffitti/posts/1343390317452659/": {
      "reason": "AI_NOT_RELEVANT",
      "timestamp": "2025-09-08T15:28:24.823569"
    },
    "https://www.facebook.com/groups/1800846897105933/posts/2152839905239962/": {
      "reason": "AI_NOT_RELEVANT",
      "timestamp": "2025-09-08T15:29:06.936179"
    },
    "https://www.facebook.com/groups/1800846897105933/posts/2152838891906730/": {
      "reason": "AI_NOT_RELEVANT",
      "timestamp": "2025-09-08T15:29:06.938006"
    },
    "https://www.facebook.com/groups/1800846897105933/posts/2152826891907930/": {
      "reason": "AI_NOT_RELEVANT",
      "timestamp": "2025-09-08T15:29:06.939884"
    },
    "https://www.facebook.com/groups/1800846897105933/posts/2152824691908150/": {
      "reason": "AI_NOT_RELEVANT",
      "timestamp": "2025-09-08T15:29:45.565513"
    },
    "https://www.facebook.com/groups/affitti.stanze.studenti.roma/posts/2712605208938447/": {
      "reason": "AI_NOT_RELEVANT",
      "timestamp": "2025-09-08T15:30:28.774565"
    },
    "https://www.facebook.com/groups/affitti.stanze.studenti.roma/posts/2700419410157027/": {
      "reason": "AI_NOT_RELEVANT",
      "timestamp": "2025-09-08T15:30:28.776432"
    },
    "https://www.facebook.com/groups/affitti.stanze.studenti.roma/posts/2679006408964994/": {
      "reason": "AI_NOT_RELEVANT",
      "timestamp": "2025-09-08T15:31:07.719632"
    },
    "https://www.facebook.com/groups/affitti.stanze.studenti.roma/posts/2677518465780455/": {
      "reason": "AI_NOT_RELEVANT",
      "timestamp": "2025-09-08T15:31:07.722817"
    },
    "https://www.facebook.com/groups/affitti.stanze.studenti.roma/posts/2674223522776616/": {
      "reason": "AI_NOT_RELEVANT",
      "timestamp": "2025-09-08T15:31:07.726260"
    },
    "https://www.facebook.com/groups/affitti.stanze.studenti.roma/posts/2662668060598829/": {
      "reason": "AI_NOT_RELEVANT",
      "timestamp": "2025-09-08T15:31:45.250422"
    },
    "https://www.facebook.com/groups/affitti.stanze.studenti.roma/posts/2655241281341507/": {
      "reason": "AI_NOT_RELEVANT",
      "timestamp": "2025-09-08T15:31:45.252307"
    },
    "https://www.facebook.com/groups/AffittoCaseRoma/posts/31132379159740175/": {
      "reason": "AI_NOT_RELEVANT",
      "timestamp": "2025-09-08T15:32:24.391236"
    },
    "https://www.facebook.com/groups/AffittoCaseRoma/posts/31132189506425807/": {
      "reason": "AI_NOT_RELEVANT",
      "timestamp": "2025-09-08T15:32:24.393110"
    },
    "https://www.facebook.com/groups/AffittoCaseRoma/posts/31132025909775500/": {
      "reason": "AI_NOT_RELEVANT",
      "timestamp": "2025-09-08T15:33:04.388274"
    },
    "https://www.facebook.com/groups/AffittoCaseRoma/posts/31131976466447111/": {
      "reason": "AI_NOT_RELEVANT",
      "timestamp": "2025-09-08T15:33:04.390205"
    },
    "https://www.facebook.com/groups/AffittoCaseRoma/posts/31131826736462084/": {
      "reason": "AI_NOT_RELEVANT",
      "timestamp": "2025-09-08T15:33:04.393477"
    },
    "https://www.facebook.com/groups/AffittoCaseRoma/posts/31131395769838514/": {
      "reason": "AI_NOT_RELEVANT",
      "timestamp": "2025-09-08T15:33:42.978439"
    },
    "https://www.facebook.com/groups/AffittoCaseRoma/posts/31131390069839084/": {
      "reason": "AI_NOT_RELEVANT",
      "timestamp": "2025-09-08T15:33:42.980358"
    },
    "https://www.facebook.com/groups/633912783969846/posts/1715548805806233/": {
      "reason": "AI_NOT_RELEVANT",
      "timestamp": "2025-09-08T15:34:56.475786"
    },
    "https://www.facebook.com/groups/633912783969846/posts/1715545215806592/": {
      "reason": "AI_NOT_RELEVANT",
      "timestamp": "2025-09-08T15:34:56.477756"
    },
    "https://www.facebook.com/groups/romaffitti/posts/1343571390767885/": {
      "reason": "AI_NOT_RELEVANT",
      "timestamp": "2025-09-08T16:32:45.434011"
    },
    "https://www.facebook.com/groups/romaffitti/posts/1343571250767899/": {
      "reason": "AI_NOT_RELEVANT",
      "timestamp": "2025-09-08T16:32:45.435884"
    },
    "https://www.facebook.com/groups/romaffitti/posts/1343568954101462/": {
      "reason": "AI_NOT_RELEVANT",
      "timestamp": "2025-09-08T16:33:23.307035"
    },
    "https://www.facebook.com/groups/romaffitti/posts/1343568850768139/": {
      "reason": "AI_NOT_RELEVANT",
      "timestamp": "2025-09-08T16:33:23.308849"
    },
    "https://www.facebook.com/groups/romaffitti/posts/1343568204101537/": {
      "reason": "AI_NOT_RELEVANT",
      "timestamp": "2025-09-08T16:33:23.310831"
    },
    "https://www.facebook.com/groups/romaffitti/posts/1343564344101923/": {
      "reason": "AI_NOT_RELEVANT",
      "timestamp": "2025-09-08T16:34:04.153191"
    },
    "https://www.facebook.com/groups/romaffitti/posts/1343543930770631/": {
      "reason": "AI_NOT_RELEVANT",
      "timestamp": "2025-09-08T16:34:04.157609"
    },
    "https://www.facebook.com/groups/romaffitti/posts/1343531630771861/": {
      "reason": "AI_NOT_RELEVANT",
      "timestamp": "2025-09-08T16:34:42.760494"
    },
    "https://www.facebook.com/groups/romaffitti/posts/1343529110772113/": {
      "reason": "AI_NOT_RELEVANT",
      "timestamp": "2025-09-08T16:34:42.763772"
    },
    "https://www.facebook.com/groups/romaffitti/posts/1343521277439563/": {
      "reason": "AI_NOT_RELEVANT",
      "timestamp": "2025-09-08T16:34:42.767222"
    },
    "https://www.facebook.com/groups/romaffitti/posts/1343521230772901/": {
      "reason": "AI_NOT_RELEVANT",
      "timestamp": "2025-09-08T16:35:28.083206"
    },
    "https://www.facebook.com/groups/romaffitti/posts/1343397867451904/": {
      "reason": "AI_NOT_RELEVANT",
      "timestamp": "2025-09-08T16:35:28.085929"
    },
    "https://www.facebook.com/groups/1800846897105933/posts/2152885681902051/": {
      "reason": "AI_NOT_RELEVANT",
      "timestamp": "2025-09-08T16:36:51.802224"
    },
    "https://www.facebook.com/groups/affitti.stanze.studenti.roma/posts/2740141839518117/": {
      "reason": "AI_NOT_RELEVANT",
      "timestamp": "2025-09-08T16:37:30.444452"
    },
    "https://www.facebook.com/groups/affitti.stanze.studenti.roma/posts/2740137142851920/": {
      "reason": "AI_NOT_RELEVANT",
      "timestamp": "2025-09-08T16:37:30.446345"
    },
    "https://www.facebook.com/groups/affitti.stanze.studenti.roma/posts/2740127796186188/": {
      "reason": "AI_NOT_RELEVANT",
      "timestamp": "2025-09-08T16:37:30.448169"
    },
    "https://www.facebook.com/groups/affitti.stanze.studenti.roma/posts/2740109756187992/": {
      "reason": "AI_NOT_RELEVANT",
      "timestamp": "2025-09-08T16:38:11.292370"
    },
    "https://www.facebook.com/groups/affitti.stanze.studenti.roma/posts/2740107512854883/": {
      "reason": "AI_NOT_RELEVANT",
      "timestamp": "2025-09-08T16:38:11.294215"
    },
    "https://www.facebook.com/groups/affitti.stanze.studenti.roma/posts/2740105309521770/": {
      "reason": "AI_NOT_RELEVANT",
      "timestamp": "2025-09-08T16:38:53.888301"
    },
    "https://www.facebook.com/groups/AffittoCaseRoma/posts/31133178472993577/": {
      "reason": "AI_NOT_RELEVANT",
      "timestamp": "2025-09-08T16:39:34.412528"
    },
    "https://www.facebook.com/groups/AffittoCaseRoma/posts/31132946939683397/": {
      "reason": "AI_NOT_RELEVANT",
      "timestamp": "2025-09-08T16:40:18.584040"
    },
    "https://www.facebook.com/groups/AffittoCaseRoma/posts/31132813799696711/": {
      "reason": "AI_NOT_RELEVANT",
      "timestamp": "2025-09-08T16:40:18.585919"
    },
    "https://www.facebook.com/groups/633912783969846/posts/1715594899134957/": {
      "reason": "AI_NOT_RELEVANT",
      "timestamp": "2025-09-08T16:41:33.272683"
    },
    "https://www.facebook.com/groups/633912783969846/posts/1715573799137067/": {
      "reason": "AI_NOT_RELEVANT",
      "timestamp": "2025-09-08T16:41:33.275739"
    },
    "https://www.facebook.com/groups/244234206083096/posts/2187243695115461/": {
      "reason": "AI_NOT_RELEVANT",
      "timestamp": "2025-09-08T16:42:11.375388"
    },
    "https://www.facebook.com/groups/244234206083096/posts/2187223478450816/": {
      "reason": "AI_NOT_RELEVANT",
      "timestamp": "2025-09-08T16:42:11.377415"
    },
    "https://www.facebook.com/groups/244234206083096/posts/2187220165117814/": {
      "reason": "AI_NOT_RELEVANT",
      "timestamp": "2025-09-08T16:42:11.379368"
    },
    "https://www.facebook.com/groups/244234206083096/posts/2187219475117883/": {
      "reason": "AI_NOT_RELEVANT",
      "timestamp": "2025-09-08T16:42:47.557026"
    },
    "https://www.facebook.com/groups/244234206083096/posts/2187192865120544/": {
      "reason": "AI_NOT_RELEVANT",
      "timestamp": "2025-09-08T16:42:47.558979"
    },
    "https://www.facebook.com/groups/AffittoCaseRoma/posts/31133757996268958/": {
      "reason": "AI_NOT_RELEVANT",
      "timestamp": "2025-09-08T17:25:15.218884"
    },
    "https://www.facebook.com/groups/AffittoCaseRoma/posts/31133565809621510/": {
      "reason": "AI_NOT_RELEVANT",
      "timestamp": "2025-09-08T17:25:15.220865"
    },
    "https://www.facebook.com/groups/AffittoCaseRoma/posts/31131285026516255/": {
      "reason": "AI_NOT_RELEVANT",
      "timestamp": "2025-09-08T17:25:54.762030"
    },
    "https://www.facebook.com/groups/244234206083096/posts/2187305575109273/": {
      "reason": "AI_NOT_RELEVANT",
      "timestamp": "2025-09-08T17:26:29.908181"
    },
    "https://www.facebook.com/groups/romaffitti/posts/1343641737427517/": {
      "reason": "AI_NOT_RELEVANT",
      "timestamp": "2025-09-08T18:39:05.679432"
    },
    "https://www.facebook.com/groups/romaffitti/posts/1343393837452307/": {
      "reason": "AI_NOT_RELEVANT",
      "timestamp": "2025-09-08T18:39:05.682106"
    },
    "https://www.facebook.com/groups/1800846897105933/posts/2152947811895838/": {
      "reason": "AI_NOT_RELEVANT",
      "timestamp": "2025-09-08T18:39:44.589663"
    },
    "https://www.facebook.com/groups/1800846897105933/posts/2152945278562758/": {
      "reason": "AI_NOT_RELEVANT",
      "timestamp": "2025-09-08T18:39:44.593946"
    },
    "https://www.facebook.com/groups/affitti.stanze.studenti.roma/posts/2740226786176289/": {
      "reason": "AI_NOT_RELEVANT",
      "timestamp": "2025-09-08T18:40:23.729215"
    },
    "https://www.facebook.com/groups/affitti.stanze.studenti.roma/posts/2740224889509812/": {
      "reason": "AI_NOT_RELEVANT",
      "timestamp": "2025-09-08T18:40:23.731151"
    },
    "https://www.facebook.com/groups/affitti.stanze.studenti.roma/posts/2740219569510344/": {
      "reason": "AI_NOT_RELEVANT",
      "timestamp": "2025-09-08T18:40:23.733126"
    },
    "https://www.facebook.com/groups/affitti.stanze.studenti.roma/posts/2740213756177592/": {
      "reason": "AI_NOT_RELEVANT",
      "timestamp": "2025-09-08T18:41:03.012111"
    },
    "https://www.facebook.com/groups/AffittoCaseRoma/posts/31134493962862028/": {
      "reason": "AI_NOT_RELEVANT",
      "timestamp": "2025-09-08T18:41:48.306689"
    },
    "https://www.facebook.com/groups/AffittoCaseRoma/posts/31134144199563671/": {
      "reason": "AI_NOT_RELEVANT",
      "timestamp": "2025-09-08T18:41:48.309732"
    },
    "https://www.facebook.com/groups/633912783969846/posts/1715667872460993/": {
      "reason": "AI_NOT_RELEVANT",
      "timestamp": "2025-09-08T18:42:28.498175"
    },
    "https://www.facebook.com/groups/633912783969846/posts/1715665815794532/": {
      "reason": "AI_NOT_RELEVANT",
      "timestamp": "2025-09-08T18:42:28.500213"
    },
    "https://www.facebook.com/groups/633912783969846/posts/1715662345794879/": {
      "reason": "AI_NOT_RELEVANT",
      "timestamp": "2025-09-08T18:42:28.504635"
    },
    "https://www.facebook.com/groups/romaffitti/posts/1343699427421748/": {
      "reason": "AI_NOT_RELEVANT",
      "timestamp": "2025-09-08T20:32:12.120837"
    },
    "https://www.facebook.com/groups/romaffitti/posts/1343672214091136/": {
      "reason": "AI_NOT_RELEVANT",
      "timestamp": "2025-09-08T20:32:12.122861"
    },
    "https://www.facebook.com/groups/1800846897105933/posts/2152992761891343/": {
      "reason": "AI_NOT_RELEVANT",
      "timestamp": "2025-09-08T20:33:27.225628"
    },
    "https://www.facebook.com/groups/1800846897105933/posts/2152978538559432/": {
      "reason": "AI_NOT_RELEVANT",
      "timestamp": "2025-09-08T20:33:27.234517"
    },
    "https://www.facebook.com/groups/1800846897105933/posts/2152978308559455/": {
      "reason": "AI_NOT_RELEVANT",
      "timestamp": "2025-09-08T20:34:05.781481"
    },
    "https://www.facebook.com/groups/1800846897105933/posts/2152810501909569/": {
      "reason": "AI_NOT_RELEVANT",
      "timestamp": "2025-09-08T20:34:05.783605"
    },
    "https://www.facebook.com/groups/affitti.stanze.studenti.roma/posts/2740307139501587/": {
      "reason": "AI_NOT_RELEVANT",
      "timestamp": "2025-09-08T20:34:43.163839"
    },
    "https://www.facebook.com/groups/affitti.stanze.studenti.roma/posts/2740306869501614/": {
      "reason": "AI_NOT_RELEVANT",
      "timestamp": "2025-09-08T20:34:43.165851"
    },
    "https://www.facebook.com/groups/affitti.stanze.studenti.roma/posts/2740297026169265/": {
      "reason": "AI_NOT_RELEVANT",
      "timestamp": "2025-09-08T20:34:43.169307"
    },
    "https://www.facebook.com/groups/affitti.stanze.studenti.roma/posts/2740299389502362/": {
      "reason": "AI_NOT_RELEVANT",
      "timestamp": "2025-09-08T20:35:20.721416"
    },
    "https://www.facebook.com/groups/affitti.stanze.studenti.roma/posts/2740266276172340/": {
      "reason": "AI_NOT_RELEVANT",
      "timestamp": "2025-09-08T20:35:20.723480"
    },
    "https://www.facebook.com/groups/affitti.stanze.studenti.roma/posts/2740254199506881/": {
      "reason": "AI_NOT_RELEVANT",
      "timestamp": "2025-09-08T20:35:20.725747"
    },
    "https://www.facebook.com/groups/affitti.stanze.studenti.roma/posts/2740243439507957/": {
      "reason": "AI_NOT_RELEVANT",
      "timestamp": "2025-09-08T20:35:56.484419"
    },
    "https://www.facebook.com/groups/affitti.stanze.studenti.roma/posts/2740246136174354/": {
      "reason": "AI_NOT_RELEVANT",
      "timestamp": "2025-09-08T20:35:56.486470"
    },
    "https://www.facebook.com/groups/affitti.stanze.studenti.roma/posts/2740241649508136/": {
      "reason": "AI_NOT_RELEVANT",
      "timestamp": "2025-09-08T20:35:56.488556"
    },
    "https://www.facebook.com/groups/AffittoCaseRoma/posts/31136116529366438/": {
      "reason": "AI_NOT_RELEVANT",
      "timestamp": "2025-09-08T20:37:07.137344"
    },
    "https://www.facebook.com/groups/AffittoCaseRoma/posts/31135125229465568/": {
      "reason": "AI_NOT_RELEVANT",
      "timestamp": "2025-09-08T20:37:07.139363"
    },
    "https://www.facebook.com/groups/633912783969846/posts/1715730205788093/": {
      "reason": "AI_NOT_RELEVANT",
      "timestamp": "2025-09-08T20:39:05.481122"
    },
    "https://www.facebook.com/groups/633912783969846/posts/1715729452454835/": {
      "reason": "AI_NOT_RELEVANT",
      "timestamp": "2025-09-08T20:39:05.483149"
    },
    "https://www.facebook.com/groups/633912783969846/posts/1715728049121642/": {
      "reason": "AI_NOT_RELEVANT",
      "timestamp": "2025-09-08T20:39:05.485523"
    },
    "https://www.facebook.com/groups/633912783969846/posts/1715701995790914/": {
      "reason": "AI_NOT_RELEVANT",
      "timestamp": "2025-09-08T20:39:42.082626"
    },
    "https://www.facebook.com/groups/633912783969846/posts/1715697265791387/": {
      "reason": "AI_NOT_RELEVANT",
      "timestamp": "2025-09-08T20:39:42.084668"
    },
    "https://www.facebook.com/groups/633912783969846/posts/1715689379125509/": {
      "reason": "AI_NOT_RELEVANT",
      "timestamp": "2025-09-08T20:39:42.086964"
    },
    "https://www.facebook.com/groups/244234206083096/posts/2187445921761905/": {
      "reason": "AI_NOT_RELEVANT",
      "timestamp": "2025-09-08T20:41:04.671781"
    },
    "https://www.facebook.com/groups/244234206083096/posts/2187445048428659/": {
      "reason": "AI_NOT_RELEVANT",
      "timestamp": "2025-09-08T20:41:04.673871"
    },
    "https://www.facebook.com/groups/1800846897105933/posts/2153049715218981/": {
      "reason": "AI_NOT_RELEVANT",
      "timestamp": "2025-09-08T21:25:15.105868"
    },
    "https://www.facebook.com/groups/1800846897105933/posts/2153048305219122/": {
      "reason": "AI_NOT_RELEVANT",
      "timestamp": "2025-09-08T21:25:15.107953"
    },
    "https://www.facebook.com/groups/1800846897105933/posts/2153040448553241/": {
      "reason": "AI_NOT_RELEVANT",
      "timestamp": "2025-09-08T21:25:52.553209"
    },
    "https://www.facebook.com/groups/1800846897105933/posts/2153003951890224/": {
      "reason": "AI_NOT_RELEVANT",
      "timestamp": "2025-09-08T21:25:52.555399"
    },
    "https://www.facebook.com/groups/affitti.stanze.studenti.roma/posts/2740237866175181/": {
      "reason": "AI_NOT_RELEVANT",
      "timestamp": "2025-09-08T21:26:28.492053"
    },
    "https://www.facebook.com/groups/AffittoCaseRoma/posts/31133068489671242/": {
      "reason": "AI_NOT_RELEVANT",
      "timestamp": "2025-09-08T21:27:07.082111"
    },
    "https://www.facebook.com/groups/633912783969846/posts/1715751452452635/": {
      "reason": "AI_NOT_RELEVANT",
      "timestamp": "2025-09-08T21:27:44.987522"
    },
    "https://www.facebook.com/groups/633912783969846/posts/1715735389120908/": {
      "reason": "AI_NOT_RELEVANT",
      "timestamp": "2025-09-08T21:27:44.989670"
    },
    "https://www.facebook.com/groups/633912783969846/posts/1715735265787587/": {
      "reason": "AI_NOT_RELEVANT",
      "timestamp": "2025-09-08T21:27:44.991837"
    },
    "https://www.facebook.com/groups/633912783969846/posts/1715672235793890/": {
      "reason": "AI_NOT_RELEVANT",
      "timestamp": "2025-09-08T21:28:20.934345"
    },
    "https://www.facebook.com/groups/244234206083096/posts/2187452641761233/": {
      "reason": "AI_NOT_RELEVANT",
      "timestamp": "2025-09-08T21:28:57.417543"
    },
    "https://www.facebook.com/groups/244234206083096/posts/2187451348428029/": {
      "reason": "AI_NOT_RELEVANT",
      "timestamp": "2025-09-08T21:28:57.419728"
    },
    "https://www.facebook.com/groups/romaffitti/posts/1343686600756364/": {
      "reason": "AI_NOT_RELEVANT",
      "timestamp": "2025-09-08T22:25:35.610184"
    },
    "https://www.facebook.com/groups/romaffitti/posts/1343617507429940/": {
      "reason": "AI_NOT_RELEVANT",
      "timestamp": "2025-09-08T22:25:35.619634"
    },
    "https://www.facebook.com/groups/1800846897105933/posts/2153087445215208/": {
      "reason": "AI_NOT_RELEVANT",
      "timestamp": "2025-09-08T22:26:12.879054"
    },
    "https://www.facebook.com/groups/1800846897105933/posts/2153084865215466/": {
      "reason": "AI_NOT_RELEVANT",
      "timestamp": "2025-09-08T22:26:12.882600"
    },
    "https://www.facebook.com/groups/1800846897105933/posts/2153000261890593/": {
      "reason": "AI_NOT_RELEVANT",
      "timestamp": "2025-09-08T22:26:49.646577"
    },
    "https://www.facebook.com/groups/affitti.stanze.studenti.roma/posts/2740365329495768/": {
      "reason": "AI_NOT_RELEVANT",
      "timestamp": "2025-09-08T22:27:27.564168"
    },
    "https://www.facebook.com/groups/affitti.stanze.studenti.roma/posts/2740363279495973/": {
      "reason": "AI_NOT_RELEVANT",
      "timestamp": "2025-09-08T22:27:27.566239"
    },
    "https://www.facebook.com/groups/affitti.stanze.studenti.roma/posts/2740340189498282/": {
      "reason": "AI_NOT_RELEVANT",
      "timestamp": "2025-09-08T22:28:05.490052"
    },
    "https://www.facebook.com/groups/affitti.stanze.studenti.roma/posts/2740339226165045/": {
      "reason": "AI_NOT_RELEVANT",
      "timestamp": "2025-09-08T22:28:05.493624"
    },
    "https://www.facebook.com/groups/affitti.stanze.studenti.roma/posts/2740331459499155/": {
      "reason": "AI_NOT_RELEVANT",
      "timestamp": "2025-09-08T22:28:44.446852"
    },
    "https://www.facebook.com/groups/633912783969846/posts/1715771912450589/": {
      "reason": "AI_NOT_RELEVANT",
      "timestamp": "2025-09-08T22:29:22.109049"
    },
    "https://www.facebook.com/groups/romaffitti/posts/1343754877416203/": {
      "reason": "AI_NOT_RELEVANT",
      "timestamp": "2025-09-08T23:26:29.796991"
    },
    "https://www.facebook.com/groups/romaffitti/posts/1343752574083100/": {
      "reason": "AI_NOT_RELEVANT",
      "timestamp": "2025-09-08T23:26:29.799055"
    },
    "https://www.facebook.com/groups/romaffitti/posts/1343749100750114/": {
      "reason": "AI_NOT_RELEVANT",
      "timestamp": "2025-09-08T23:26:29.801262"
    },
    "https://www.facebook.com/groups/romaffitti/posts/1343741607417530/": {
      "reason": "AI_NOT_RELEVANT",
      "timestamp": "2025-09-08T23:27:06.009937"
    },
    "https://www.facebook.com/groups/romaffitti/posts/1343669304091427/": {
      "reason": "AI_NOT_RELEVANT",
      "timestamp": "2025-09-08T23:27:06.012029"
    },
    "https://www.facebook.com/groups/1800846897105933/posts/2153116875212265/": {
      "reason": "AI_NOT_RELEVANT",
      "timestamp": "2025-09-08T23:27:43.345307"
    },
    "https://www.facebook.com/groups/1800846897105933/posts/2153116731878946/": {
      "reason": "AI_NOT_RELEVANT",
      "timestamp": "2025-09-08T23:27:43.347410"
    },
    "https://www.facebook.com/groups/1800846897105933/posts/2153104218546864/": {
      "reason": "AI_NOT_RELEVANT",
      "timestamp": "2025-09-08T23:27:43.349582"
    },
    "https://www.facebook.com/groups/affitti.stanze.studenti.roma/posts/2740394972826137/": {
      "reason": "AI_NOT_RELEVANT",
      "timestamp": "2025-09-08T23:28:55.216580"
    },
    "https://www.facebook.com/groups/affitti.stanze.studenti.roma/posts/2740392912826343/": {
      "reason": "AI_NOT_RELEVANT",
      "timestamp": "2025-09-08T23:28:55.218766"
    },
    "https://www.facebook.com/groups/633912783969846/posts/1715804559113991/": {
      "reason": "AI_NOT_RELEVANT",
      "timestamp": "2025-09-08T23:30:03.501685"
    },
    "https://www.facebook.com/groups/romaffitti/posts/1343797280745296/": {
      "reason": "AI_NOT_RELEVANT",
      "timestamp": "2025-09-09T01:56:35.546031"
    },
    "https://www.facebook.com/groups/romaffitti/posts/1343783774079980/": {
      "reason": "AI_NOT_RELEVANT",
      "timestamp": "2025-09-09T01:56:35.548209"
    },
    "https://www.facebook.com/groups/romaffitti/posts/1343773837414307/": {
      "reason": "AI_NOT_RELEVANT",
      "timestamp": "2025-09-09T01:56:35.550480"
    },
    "https://www.facebook.com/groups/1800846897105933/posts/2153130971877522/": {
      "reason": "AI_NOT_RELEVANT",
      "timestamp": "2025-09-09T01:57:50.595168"
    },
    "https://www.facebook.com/groups/1800846897105933/posts/2153124525211500/": {
      "reason": "AI_NOT_RELEVANT",
      "timestamp": "2025-09-09T01:57:50.597258"
    },
    "https://www.facebook.com/groups/1800846897105933/posts/2153123161878303/": {
      "reason": "AI_NOT_RELEVANT",
      "timestamp": "2025-09-09T01:57:50.599328"
    },
    "https://www.facebook.com/groups/AffittoCaseRoma/posts/31138138445830913/": {
      "reason": "AI_NOT_RELEVANT",
      "timestamp": "2025-09-09T01:59:39.629041"
    },
    "https://www.facebook.com/groups/AffittoCaseRoma/posts/31137473535897404/": {
      "reason": "AI_NOT_RELEVANT",
      "timestamp": "2025-09-09T01:59:39.631186"
    },
    "https://www.facebook.com/groups/633912783969846/posts/1715824535778660/": {
      "reason": "AI_NOT_RELEVANT",
      "timestamp": "2025-09-09T02:00:22.646488"
    },
    "https://www.facebook.com/groups/633912783969846/posts/1715815809112866/": {
      "reason": "AI_NOT_RELEVANT",
      "timestamp": "2025-09-09T02:00:22.648634"
    },
    "https://www.facebook.com/groups/633912783969846/posts/1715814745779639/": {
      "reason": "AI_NOT_RELEVANT",
      "timestamp": "2025-09-09T02:00:22.650731"
    },
    "https://www.facebook.com/groups/633912783969846/posts/1715812025779911/": {
      "reason": "AI_NOT_RELEVANT",
      "timestamp": "2025-09-09T02:00:56.430168"
    },
    "https://www.facebook.com/groups/affitti.stanze.studenti.roma/posts/2740409079491393/": {
      "reason": "AI_NOT_RELEVANT",
      "timestamp": "2025-09-09T04:32:14.112595"
    },
    "https://www.facebook.com/groups/1800846897105933/posts/2153246248532661/": {
      "reason": "AI_NOT_RELEVANT",
      "timestamp": "2025-09-09T05:25:56.213133"
    },
    "https://www.facebook.com/groups/romaffitti/posts/1343989847392706/": {
      "reason": "AI_NOT_RELEVANT",
      "timestamp": "2025-09-09T06:37:27.466141"
    },
    "https://www.facebook.com/groups/romaffitti/posts/1343989060726118/": {
      "reason": "AI_NOT_RELEVANT",
      "timestamp": "2025-09-09T06:37:27.468413"
    },
    "https://www.facebook.com/groups/romaffitti/posts/1343952120729812/": {
      "reason": "AI_NOT_RELEVANT",
      "timestamp": "2025-09-09T06:38:06.301729"
    },
    "https://www.facebook.com/groups/romaffitti/posts/1343739790751045/": {
      "reason": "AI_NOT_RELEVANT",
      "timestamp": "2025-09-09T06:38:06.303926"
    },
    "https://www.facebook.com/groups/1800846897105933/posts/2153327248524561/": {
      "reason": "AI_NOT_RELEVANT",
      "timestamp": "2025-09-09T06:38:45.435402"
    },
    "https://www.facebook.com/groups/1800846897105933/posts/2153319638525322/": {
      "reason": "AI_NOT_RELEVANT",
      "timestamp": "2025-09-09T06:38:45.437618"
    },
    "https://www.facebook.com/groups/AffittoCaseRoma/posts/31141682508809840/": {
      "reason": "AI_NOT_RELEVANT",
      "timestamp": "2025-09-09T06:39:23.084207"
    },
    "https://www.facebook.com/groups/AffittoCaseRoma/posts/31141555285489229/": {
      "reason": "AI_NOT_RELEVANT",
      "timestamp": "2025-09-09T06:39:23.086388"
    },
    "https://www.facebook.com/groups/1800846897105933/posts/2153351311855488/": {
      "reason": "AI_NOT_RELEVANT",
      "timestamp": "2025-09-09T07:27:32.857597"
    },
    "https://www.facebook.com/groups/1800846897105933/posts/2153347741855845/": {
      "reason": "AI_NOT_RELEVANT",
      "timestamp": "2025-09-09T07:27:32.859832"
    },
    "https://www.facebook.com/groups/633912783969846/posts/1716026815758432/": {
      "reason": "AI_NOT_RELEVANT",
      "timestamp": "2025-09-09T07:30:10.846502"
    },
    "https://www.facebook.com/groups/633912783969846/posts/1716010499093397/": {
      "reason": "AI_NOT_RELEVANT",
      "timestamp": "2025-09-09T07:30:10.848668"
    },
    "https://www.facebook.com/groups/633912783969846/posts/1715671159127331/": {
      "reason": "AI_NOT_RELEVANT",
      "timestamp": "2025-09-09T07:30:46.684606"
    },
    "https://www.facebook.com/groups/romaffitti/posts/1344020207389670/": {
      "reason": "AI_NOT_RELEVANT",
      "timestamp": "2025-09-09T08:35:58.219911"
    },
    "https://www.facebook.com/groups/romaffitti/posts/1344018704056487/": {
      "reason": "AI_NOT_RELEVANT",
      "timestamp": "2025-09-09T08:35:58.222120"
    },
    "https://www.facebook.com/groups/romaffitti/posts/1344017224056635/": {
      "reason": "AI_NOT_RELEVANT",
      "timestamp": "2025-09-09T08:35:58.224443"
    },
    "https://www.facebook.com/groups/romaffitti/posts/1344014197390271/": {
      "reason": "AI_NOT_RELEVANT",
      "timestamp": "2025-09-09T08:36:36.680886"
    },
    "https://www.facebook.com/groups/romaffitti/posts/1344013027390388/": {
      "reason": "AI_NOT_RELEVANT",
      "timestamp": "2025-09-09T08:36:36.683230"
    },
    "https://www.facebook.com/groups/romaffitti/posts/1343932507398440/": {
      "reason": "AI_NOT_RELEVANT",
      "timestamp": "2025-09-09T08:37:18.999215"
    },
    "https://www.facebook.com/groups/1800846897105933/posts/2153395231851096/": {
      "reason": "AI_NOT_RELEVANT",
      "timestamp": "2025-09-09T08:37:56.017263"
    },
    "https://www.facebook.com/groups/1800846897105933/posts/2153394191851200/": {
      "reason": "AI_NOT_RELEVANT",
      "timestamp": "2025-09-09T08:37:56.019477"
    },
    "https://www.facebook.com/groups/1800846897105933/posts/2153394048517881/": {
      "reason": "AI_NOT_RELEVANT",
      "timestamp": "2025-09-09T08:37:56.021578"
    },
    "https://www.facebook.com/groups/1800846897105933/posts/2153388035185149/": {
      "reason": "AI_NOT_RELEVANT",
      "timestamp": "2025-09-09T08:38:33.462572"
    },
    "https://www.facebook.com/groups/AffittoCaseRoma/posts/31142977005347057/": {
      "reason": "AI_NOT_RELEVANT",
      "timestamp": "2025-09-09T08:39:11.590748"
    },
    "https://www.facebook.com/groups/AffittoCaseRoma/posts/31142870892024335/": {
      "reason": "AI_NOT_RELEVANT",
      "timestamp": "2025-09-09T08:39:11.593062"
    },
    "https://www.facebook.com/groups/633912783969846/posts/1716059769088470/": {
      "reason": "AI_NOT_RELEVANT",
      "timestamp": "2025-09-09T08:39:50.548890"
    },
    "https://www.facebook.com/groups/633912783969846/posts/1716051992422581/": {
      "reason": "AI_NOT_RELEVANT",
      "timestamp": "2025-09-09T08:39:50.552013"
    },
    "https://www.facebook.com/groups/633912783969846/posts/1716049999089447/": {
      "reason": "AI_NOT_RELEVANT",
      "timestamp": "2025-09-09T08:40:30.461348"
    },
    "https://www.facebook.com/groups/633912783969846/posts/1716046875756426/": {
      "reason": "AI_NOT_RELEVANT",
      "timestamp": "2025-09-09T08:40:30.463618"
    },
    "https://www.facebook.com/groups/633912783969846/posts/1716036002424180/": {
      "reason": "AI_NOT_RELEVANT",
      "timestamp": "2025-09-09T08:40:30.465811"
    },
    "https://www.facebook.com/groups/244234206083096/posts/2187798435059987/": {
      "reason": "AI_NOT_RELEVANT",
      "timestamp": "2025-09-09T08:41:07.130266"
    },
    "https://www.facebook.com/groups/244234206083096/posts/2187787748394389/": {
      "reason": "AI_NOT_RELEVANT",
      "timestamp": "2025-09-09T08:41:07.132620"
    },
    "https://www.facebook.com/groups/romaffitti/posts/1344052194053138/": {
      "reason": "AI_NOT_RELEVANT",
      "timestamp": "2025-09-09T09:29:32.594549"
    },
    "https://www.facebook.com/groups/romaffitti/posts/1344051690719855/": {
      "reason": "AI_NOT_RELEVANT",
      "timestamp": "2025-09-09T09:29:32.596807"
    },
    "https://www.facebook.com/groups/romaffitti/posts/1344051607386530/": {
      "reason": "AI_NOT_RELEVANT",
      "timestamp": "2025-09-09T09:29:32.599272"
    },
    "https://www.facebook.com/groups/romaffitti/posts/1344050187386672/": {
      "reason": "AI_NOT_RELEVANT",
      "timestamp": "2025-09-09T09:30:08.376927"
    },
    "https://www.facebook.com/groups/romaffitti/posts/1344048644053493/": {
      "reason": "AI_NOT_RELEVANT",
      "timestamp": "2025-09-09T09:30:08.379198"
    },
    "https://www.facebook.com/groups/romaffitti/posts/1344048630720161/": {
      "reason": "AI_NOT_RELEVANT",
      "timestamp": "2025-09-09T09:30:08.381378"
    },
    "https://www.facebook.com/groups/1800846897105933/posts/2153428128514473/": {
      "reason": "AI_NOT_RELEVANT",
      "timestamp": "2025-09-09T09:30:44.543968"
    },
    "https://www.facebook.com/groups/1800846897105933/posts/2153427958514490/": {
      "reason": "AI_NOT_RELEVANT",
      "timestamp": "2025-09-09T09:30:44.546224"
    },
    "https://www.facebook.com/groups/AffittoCaseRoma/posts/31143709008607190/": {
      "reason": "AI_NOT_RELEVANT",
      "timestamp": "2025-09-09T09:31:20.630649"
    },
    "https://www.facebook.com/groups/AffittoCaseRoma/posts/31143168255327932/": {
      "reason": "AI_NOT_RELEVANT",
      "timestamp": "2025-09-09T09:31:20.632924"
    },
    "https://rss.app": {
      "reason": "AI_NOT_RELEVANT",
      "timestamp": "2025-09-09T10:32:21.035534"
    }
  },
  "total_rejected_count": 2899,
  "timestamp": "2025-09-09T20:27:45.310109"
}