{
  "urls": {
    "https://www.facebook.com/groups/181439002455412/posts/1839219986677297/": {
      "reason": "AI_NOT_RELEVANT",
      "timestamp": "2025-08-28T16:41:06.144526"
    },
    "https://www.facebook.com/groups/181439002455412/posts/1839108046688491/": {
      "reason": "AI_NOT_RELEVANT",
      "timestamp": "2025-08-28T16:41:49.525795"
    },
    "https://www.facebook.com/groups/478152972719598/posts/2110560736145472/": {
      "reason": "AI_NOT_RELEVANT",
      "timestamp": "2025-08-28T16:42:26.537600"
    },
    "https://www.facebook.com/groups/478152972719598/posts/2110557539479125/": {
      "reason": "AI_NOT_RELEVANT",
      "timestamp": "2025-08-28T16:42:26.538398"
    },
    "https://www.facebook.com/groups/478152972719598/posts/2110552589479620/": {
      "reason": "AI_NOT_RELEVANT",
      "timestamp": "2025-08-28T16:42:26.539293"
    },
    "https://www.facebook.com/groups/181439002455412/posts/1839262490006380/": {
      "reason": "AI_NOT_RELEVANT",
      "timestamp": "2025-08-28T17:28:29.188828"
    },
    "https://www.facebook.com/groups/181439002455412/posts/1839259133340049/": {
      "reason": "AI_NOT_RELEVANT",
      "timestamp": "2025-08-28T17:29:10.669519"
    },
    "https://www.facebook.com/groups/181439002455412/posts/1839259006673395/": {
      "reason": "AI_NOT_RELEVANT",
      "timestamp": "2025-08-28T17:29:10.670378"
    },
    "https://www.facebook.com/groups/181439002455412/posts/1839255250007104/": {
      "reason": "AI_NOT_RELEVANT",
      "timestamp": "2025-08-28T17:29:10.671534"
    },
    "https://www.facebook.com/groups/478152972719598/posts/2110551579479721/": {
      "reason": "AI_NOT_RELEVANT",
      "timestamp": "2025-08-28T17:29:46.400253"
    },
    "https://www.facebook.com/groups/1075915486829306/posts/1421085045645680/": {
      "reason": "AI_NOT_RELEVANT",
      "timestamp": "2025-08-28T18:40:53.008370"
    },
    "https://www.facebook.com/groups/1075915486829306/posts/1421013138986204/": {
      "reason": "AI_NOT_RELEVANT",
      "timestamp": "2025-08-28T18:41:34.462256"
    },
    "https://www.facebook.com/groups/1075915486829306/posts/1421005412320310/": {
      "reason": "AI_NOT_RELEVANT",
      "timestamp": "2025-08-28T18:41:34.462883"
    },
    "https://www.facebook.com/groups/478152972719598/posts/2110671642801048/": {
      "reason": "AI_NOT_RELEVANT",
      "timestamp": "2025-08-28T18:44:14.288686"
    },
    "https://www.facebook.com/groups/478152972719598/posts/2110663126135233/": {
      "reason": "AI_NOT_RELEVANT",
      "timestamp": "2025-08-28T18:44:14.290245"
    },
    "https://www.facebook.com/groups/181439002455412/posts/1839325130000116/": {
      "reason": "AI_NOT_RELEVANT",
      "timestamp": "2025-08-28T19:26:10.776864"
    },
    "https://www.facebook.com/groups/181439002455412/posts/1839321443333818/": {
      "reason": "AI_NOT_RELEVANT",
      "timestamp": "2025-08-28T19:26:10.777553"
    },
    "https://www.facebook.com/groups/478152972719598/posts/2110696866131859/": {
      "reason": "AI_NOT_RELEVANT",
      "timestamp": "2025-08-28T19:27:26.906476"
    },
    "https://www.facebook.com/groups/478152972719598/posts/2110693826132163/": {
      "reason": "AI_NOT_RELEVANT",
      "timestamp": "2025-08-28T19:27:26.907119"
    },
    "https://www.facebook.com/groups/478152972719598/posts/2110691766132369/": {
      "reason": "AI_NOT_RELEVANT",
      "timestamp": "2025-08-28T19:28:04.650909"
    },
    "https://www.facebook.com/groups/181439002455412/posts/1839365053329457/": {
      "reason": "AI_NOT_RELEVANT",
      "timestamp": "2025-08-28T20:37:57.619928"
    },
    "https://www.facebook.com/groups/181439002455412/posts/1839361316663164/": {
      "reason": "AI_NOT_RELEVANT",
      "timestamp": "2025-08-28T20:37:57.620594"
    },
    "https://www.facebook.com/groups/181439002455412/posts/1839359796663316/": {
      "reason": "AI_NOT_RELEVANT",
      "timestamp": "2025-08-28T20:38:39.952967"
    },
    "https://www.facebook.com/groups/181439002455412/posts/1839390579993571/": {
      "reason": "AI_NOT_RELEVANT",
      "timestamp": "2025-08-28T22:31:04.100884"
    },
    "https://www.facebook.com/groups/181439002455412/posts/1839390129993616/": {
      "reason": "AI_NOT_RELEVANT",
      "timestamp": "2025-08-28T22:31:04.101592"
    },
    "https://www.facebook.com/groups/478152972719598/posts/2110757962792416/": {
      "reason": "AI_NOT_RELEVANT",
      "timestamp": "2025-08-28T22:33:20.650282"
    },
    "https://www.facebook.com/groups/478152972719598/posts/2110709336130612/": {
      "reason": "AI_NOT_RELEVANT",
      "timestamp": "2025-08-28T22:33:20.650976"
    },
    "https://www.facebook.com/groups/1075915486829306/posts/1421200628967455/": {
      "reason": "AI_NOT_RELEVANT",
      "timestamp": "2025-08-28T23:29:12.417615"
    },
    "https://www.facebook.com/groups/1075915486829306/posts/1421143025639882/": {
      "reason": "AI_NOT_RELEVANT",
      "timestamp": "2025-08-28T23:29:12.418746"
    },
    "https://www.facebook.com/groups/181439002455412/posts/1839420739990555/": {
      "reason": "AI_NOT_RELEVANT",
      "timestamp": "2025-08-28T23:29:54.967800"
    },
    "https://www.facebook.com/groups/181439002455412/posts/1839420246657271/": {
      "reason": "AI_NOT_RELEVANT",
      "timestamp": "2025-08-28T23:30:30.008039"
    },
    "https://www.facebook.com/groups/181439002455412/posts/1839413363324626/": {
      "reason": "AI_NOT_RELEVANT",
      "timestamp": "2025-08-28T23:30:30.008768"
    },
    "https://www.facebook.com/groups/478152972719598/posts/2110666389468240/": {
      "reason": "AI_NOT_RELEVANT",
      "timestamp": "2025-08-28T23:31:39.928708"
    },
    "https://www.facebook.com/groups/181439002455412/posts/1839445526654743/": {
      "reason": "AI_NOT_RELEVANT",
      "timestamp": "2025-08-29T01:58:25.895368"
    },
    "https://www.facebook.com/groups/181439002455412/posts/1839431876656108/": {
      "reason": "AI_NOT_RELEVANT",
      "timestamp": "2025-08-29T01:58:25.896805"
    },
    "https://www.facebook.com/groups/181439002455412/posts/1839297143336248/": {
      "reason": "AI_NOT_RELEVANT",
      "timestamp": "2025-08-29T01:59:00.732752"
    },
    "https://www.facebook.com/groups/478152972719598/posts/2110839996117546/": {
      "reason": "AI_NOT_RELEVANT",
      "timestamp": "2025-08-29T02:00:13.203175"
    },
    "https://www.facebook.com/groups/1075915486829306/posts/1421172602303591/": {
      "reason": "AI_NOT_RELEVANT",
      "timestamp": "2025-08-29T04:29:50.043714"
    },
    "https://www.facebook.com/groups/181439002455412/posts/1839611659971463/": {
      "reason": "AI_NOT_RELEVANT",
      "timestamp": "2025-08-29T05:24:56.624059"
    },
    "https://www.facebook.com/groups/181439002455412/posts/1839592646640031/": {
      "reason": "AI_NOT_RELEVANT",
      "timestamp": "2025-08-29T05:24:56.624863"
    },
    "https://www.facebook.com/groups/478152972719598/posts/2110909266110619/": {
      "reason": "AI_NOT_RELEVANT",
      "timestamp": "2025-08-29T05:26:43.532966"
    },
    "https://www.facebook.com/groups/1075915486829306/posts/1421466358940882/": {
      "reason": "AI_NOT_RELEVANT",
      "timestamp": "2025-08-29T06:41:22.081482"
    },
    "https://www.facebook.com/groups/181439002455412/posts/1839642129968416/": {
      "reason": "AI_NOT_RELEVANT",
      "timestamp": "2025-08-29T06:41:59.009107"
    },
    "https://www.facebook.com/groups/181439002455412/posts/1839639619968667/": {
      "reason": "AI_NOT_RELEVANT",
      "timestamp": "2025-08-29T06:41:59.010261"
    },
    "https://www.facebook.com/groups/181439002455412/posts/1839482006651095/": {
      "reason": "AI_NOT_RELEVANT",
      "timestamp": "2025-08-29T06:42:37.406669"
    },
    "https://www.facebook.com/groups/478152972719598/posts/2111018422766370/": {
      "reason": "AI_NOT_RELEVANT",
      "timestamp": "2025-08-29T06:43:49.345447"
    },
    "https://www.facebook.com/groups/478152972719598/posts/2110998769435002/": {
      "reason": "AI_NOT_RELEVANT",
      "timestamp": "2025-08-29T06:43:49.346274"
    },
    "https://www.facebook.com/groups/181439002455412/posts/1839698919962737/": {
      "reason": "AI_NOT_RELEVANT",
      "timestamp": "2025-08-29T08:42:39.127037"
    },
    "https://www.facebook.com/groups/181439002455412/posts/1839698519962777/": {
      "reason": "AI_NOT_RELEVANT",
      "timestamp": "2025-08-29T08:42:39.127798"
    },
    "https://www.facebook.com/groups/181439002455412/posts/1839736486625647/": {
      "reason": "AI_NOT_RELEVANT",
      "timestamp": "2025-08-29T09:32:16.489795"
    },
    "https://www.facebook.com/groups/478152972719598/posts/2111116459423233/": {
      "reason": "AI_NOT_RELEVANT",
      "timestamp": "2025-08-29T09:33:32.750076"
    },
    "https://www.facebook.com/groups/478152972719598/posts/2111101212758091/": {
      "reason": "AI_NOT_RELEVANT",
      "timestamp": "2025-08-29T09:34:07.570490"
    },
    "https://www.facebook.com/groups/1075915486829306/posts/1421553862265465/": {
      "reason": "AI_NOT_RELEVANT",
      "timestamp": "2025-08-29T10:34:19.414797"
    },
    "https://www.facebook.com/groups/478152972719598/posts/2111130289421850/": {
      "reason": "AI_NOT_RELEVANT",
      "timestamp": "2025-08-29T10:35:33.615034"
    },
    "https://www.facebook.com/groups/478152972719598/posts/2111126386088907/": {
      "reason": "AI_NOT_RELEVANT",
      "timestamp": "2025-08-29T10:35:33.615903"
    },
    "https://www.facebook.com/groups/478152972719598/posts/2111062089428670/": {
      "reason": "AI_NOT_RELEVANT",
      "timestamp": "2025-08-29T10:36:09.297288"
    },
    "https://www.facebook.com/groups/1075915486829306/posts/1421608078926710/": {
      "reason": "AI_NOT_RELEVANT",
      "timestamp": "2025-08-29T11:30:20.142057"
    },
    "https://www.facebook.com/groups/181439002455412/posts/1839798226619473/": {
      "reason": "AI_NOT_RELEVANT",
      "timestamp": "2025-08-29T11:30:57.384282"
    },
    "https://www.facebook.com/groups/181439002455412/posts/1839796943286268/": {
      "reason": "AI_NOT_RELEVANT",
      "timestamp": "2025-08-29T11:30:57.385172"
    },
    "https://www.facebook.com/groups/181439002455412/posts/1839794049953224/": {
      "reason": "AI_NOT_RELEVANT",
      "timestamp": "2025-08-29T11:31:34.671099"
    },
    "https://www.facebook.com/groups/181439002455412/posts/1839793389953290/": {
      "reason": "AI_NOT_RELEVANT",
      "timestamp": "2025-08-29T11:31:34.671939"
    },
    "https://www.facebook.com/groups/181439002455412/posts/1839793313286631/": {
      "reason": "AI_NOT_RELEVANT",
      "timestamp": "2025-08-29T11:31:34.673279"
    },
    "https://www.facebook.com/groups/181439002455412/posts/1839790456620250/": {
      "reason": "AI_NOT_RELEVANT",
      "timestamp": "2025-08-29T11:32:09.293365"
    },
    "https://www.facebook.com/groups/181439002455412/posts/1839768959955733/": {
      "reason": "AI_NOT_RELEVANT",
      "timestamp": "2025-08-29T11:32:09.294247"
    },
    "https://www.facebook.com/groups/478152972719598/posts/2111188616082684/": {
      "reason": "AI_NOT_RELEVANT",
      "timestamp": "2025-08-29T11:33:21.586110"
    },
    "https://www.facebook.com/groups/478152972719598/posts/2111183442749868/": {
      "reason": "AI_NOT_RELEVANT",
      "timestamp": "2025-08-29T11:33:21.587019"
    },
    "https://www.facebook.com/groups/181439002455412/posts/1839833186615977/": {
      "reason": "AI_NOT_RELEVANT",
      "timestamp": "2025-08-29T13:08:50.728943"
    },
    "https://www.facebook.com/groups/181439002455412/posts/1839821636617132/": {
      "reason": "AI_NOT_RELEVANT",
      "timestamp": "2025-08-29T13:08:50.729884"
    },
    "https://www.facebook.com/groups/181439002455412/posts/1839811369951492/": {
      "reason": "AI_NOT_RELEVANT",
      "timestamp": "2025-08-29T13:08:50.731250"
    },
    "https://www.facebook.com/groups/478152972719598/posts/2111277792740433/": {
      "reason": "AI_NOT_RELEVANT",
      "timestamp": "2025-08-29T13:10:43.408609"
    },
    "https://www.facebook.com/groups/478152972719598/posts/2111268646074681/": {
      "reason": "AI_NOT_RELEVANT",
      "timestamp": "2025-08-29T13:10:43.409528"
    },
    "https://www.facebook.com/groups/478152972719598/posts/2111159572752255/": {
      "reason": "AI_NOT_RELEVANT",
      "timestamp": "2025-08-29T13:12:03.901274"
    },
    "https://www.facebook.com/groups/1075915486829306/posts/1421744385579746/": {
      "reason": "AI_NOT_RELEVANT",
      "timestamp": "2025-08-29T14:31:21.352336"
    },
    "https://www.facebook.com/groups/I6680/posts/24231916263144072/": {
      "reason": "AI_NOT_RELEVANT",
      "timestamp": "2025-08-29T14:32:02.041548"
    },
    "https://www.facebook.com/groups/478152972719598/posts/2111321579402721/": {
      "reason": "AI_NOT_RELEVANT",
      "timestamp": "2025-08-29T14:32:38.037876"
    },
    "https://www.facebook.com/groups/478152972719598/posts/2111316306069915/": {
      "reason": "AI_NOT_RELEVANT",
      "timestamp": "2025-08-29T14:32:38.038795"
    },
    "https://www.facebook.com/groups/478152972719598/posts/2111311559403723/": {
      "reason": "AI_NOT_RELEVANT",
      "timestamp": "2025-08-29T14:32:38.040180"
    },
    "https://www.facebook.com/groups/478152972719598/posts/2111309302737282/": {
      "reason": "AI_NOT_RELEVANT",
      "timestamp": "2025-08-29T14:33:13.890962"
    },
    "https://www.facebook.com/groups/1075915486829306/posts/1421771622243689/": {
      "reason": "AI_NOT_RELEVANT",
      "timestamp": "2025-08-29T15:31:26.073627"
    },
    "https://www.facebook.com/groups/181439002455412/posts/1839922576607038/": {
      "reason": "AI_NOT_RELEVANT",
      "timestamp": "2025-08-29T15:32:01.599453"
    },
    "https://www.facebook.com/groups/181439002455412/posts/1839884203277542/": {
      "reason": "AI_NOT_RELEVANT",
      "timestamp": "2025-08-29T15:32:01.600405"
    },
    "https://www.facebook.com/groups/1075915486829306/posts/1421827462238105/": {
      "reason": "AI_NOT_RELEVANT",
      "timestamp": "2025-08-29T16:40:56.139101"
    },
    "https://www.facebook.com/groups/1075915486829306/posts/1421826078904910/": {
      "reason": "AI_NOT_RELEVANT",
      "timestamp": "2025-08-29T16:40:56.140573"
    },
    "https://www.facebook.com/groups/1075915486829306/posts/1421806238906894/": {
      "reason": "AI_NOT_RELEVANT",
      "timestamp": "2025-08-29T16:41:31.350885"
    },
    "https://www.facebook.com/groups/181439002455412/posts/1839998549932774/": {
      "reason": "AI_NOT_RELEVANT",
      "timestamp": "2025-08-29T16:42:20.695086"
    },
    "https://www.facebook.com/groups/181439002455412/posts/1839988523267110/": {
      "reason": "AI_NOT_RELEVANT",
      "timestamp": "2025-08-29T16:42:20.696126"
    },
    "https://www.facebook.com/groups/181439002455412/posts/1839987423267220/": {
      "reason": "AI_NOT_RELEVANT",
      "timestamp": "2025-08-29T16:42:20.697063"
    },
    "https://www.facebook.com/groups/181439002455412/posts/1839953929937236/": {
      "reason": "AI_NOT_RELEVANT",
      "timestamp": "2025-08-29T16:42:59.473507"
    },
    "https://www.facebook.com/groups/181439002455412/posts/1839886673277295/": {
      "reason": "AI_NOT_RELEVANT",
      "timestamp": "2025-08-29T16:42:59.474809"
    },
    "https://www.facebook.com/groups/478152972719598/posts/2111405099394369/": {
      "reason": "AI_NOT_RELEVANT",
      "timestamp": "2025-08-29T16:44:12.571761"
    },
    "https://www.facebook.com/groups/478152972719598/posts/2111399096061636/": {
      "reason": "AI_NOT_RELEVANT",
      "timestamp": "2025-08-29T16:44:12.573231"
    },
    "https://www.facebook.com/groups/1075915486829306/posts/1421843648903153/": {
      "reason": "AI_NOT_RELEVANT",
      "timestamp": "2025-08-29T17:23:55.846466"
    },
    "https://www.facebook.com/groups/1075915486829306/posts/1421830945571090/": {
      "reason": "AI_NOT_RELEVANT",
      "timestamp": "2025-08-29T17:23:55.848764"
    },
    "https://www.facebook.com/groups/478152972719598/posts/2111286029406276/": {
      "reason": "AI_NOT_RELEVANT",
      "timestamp": "2025-08-29T17:25:51.372494"
    },
    "https://www.facebook.com/groups/1075915486829306/posts/1421893465564838/": {
      "reason": "AI_NOT_RELEVANT",
      "timestamp": "2025-08-29T18:48:34.419864"
    },
    "https://www.facebook.com/groups/1075915486829306/posts/1421893305564854/": {
      "reason": "AI_NOT_RELEVANT",
      "timestamp": "2025-08-29T18:48:34.421370"
    },
    "https://www.facebook.com/groups/181439002455412/posts/1840018739930755/": {
      "reason": "AI_NOT_RELEVANT",
      "timestamp": "2025-08-29T18:49:17.019082"
    },
    "https://www.facebook.com/groups/181439002455412/posts/1840013073264655/": {
      "reason": "AI_NOT_RELEVANT",
      "timestamp": "2025-08-29T18:50:08.523466"
    },
    "https://www.facebook.com/groups/181439002455412/posts/1839854793280483/": {
      "reason": "AI_NOT_RELEVANT",
      "timestamp": "2025-08-29T18:50:47.797803"
    },
    "https://www.facebook.com/groups/1075915486829306/posts/1421914825562702/": {
      "reason": "AI_NOT_RELEVANT",
      "timestamp": "2025-08-29T19:24:05.835329"
    },
    "https://www.facebook.com/groups/478152972719598/posts/2111507742717438/": {
      "reason": "AI_NOT_RELEVANT",
      "timestamp": "2025-08-29T19:25:46.800022"
    },
    "https://www.facebook.com/groups/1075915486829306/posts/1421929402227911/": {
      "reason": "AI_NOT_RELEVANT",
      "timestamp": "2025-08-29T20:38:56.613580"
    },
    "https://www.facebook.com/groups/1075915486829306/posts/1421923118895206/": {
      "reason": "AI_NOT_RELEVANT",
      "timestamp": "2025-08-29T20:38:56.615986"
    },
    "https://www.facebook.com/groups/1075915486829306/posts/1421908948896623/": {
      "reason": "AI_NOT_RELEVANT",
      "timestamp": "2025-08-29T20:38:56.618559"
    },
    "https://www.facebook.com/groups/181439002455412/posts/1840086566590639/": {
      "reason": "AI_NOT_RELEVANT",
      "timestamp": "2025-08-29T20:40:12.255910"
    },
    "https://www.facebook.com/groups/181439002455412/posts/1840059523260010/": {
      "reason": "AI_NOT_RELEVANT",
      "timestamp": "2025-08-29T20:40:12.258435"
    },
    "https://www.facebook.com/groups/181439002455412/posts/1840127493253213/": {
      "reason": "AI_NOT_RELEVANT",
      "timestamp": "2025-08-29T21:26:48.119770"
    },
    "https://www.facebook.com/groups/181439002455412/posts/1840122503253712/": {
      "reason": "AI_NOT_RELEVANT",
      "timestamp": "2025-08-29T21:26:48.120862"
    },
    "https://www.facebook.com/groups/181439002455412/posts/1840116533254309/": {
      "reason": "AI_NOT_RELEVANT",
      "timestamp": "2025-08-29T21:26:48.122102"
    },
    "https://www.facebook.com/groups/478152972719598/posts/2111540422714170/": {
      "reason": "AI_NOT_RELEVANT",
      "timestamp": "2025-08-29T21:28:42.968395"
    },
    "https://www.facebook.com/groups/1075915486829306/posts/1421992305554954/": {
      "reason": "AI_NOT_RELEVANT",
      "timestamp": "2025-08-29T22:32:10.650389"
    },
    "https://www.facebook.com/groups/1075915486829306/posts/1421991792221672/": {
      "reason": "AI_NOT_RELEVANT",
      "timestamp": "2025-08-29T22:32:10.651463"
    },
    "https://www.facebook.com/groups/1075915486829306/posts/1421991668888351/": {
      "reason": "AI_NOT_RELEVANT",
      "timestamp": "2025-08-29T22:32:10.652592"
    },
    "https://www.facebook.com/groups/181439002455412/posts/1840114789921150/": {
      "reason": "AI_NOT_RELEVANT",
      "timestamp": "2025-08-29T22:33:24.268010"
    },
    "https://www.facebook.com/groups/478152972719598/posts/2111607072707505/": {
      "reason": "AI_NOT_RELEVANT",
      "timestamp": "2025-08-29T22:34:39.984003"
    },
    "https://www.facebook.com/groups/478152972719598/posts/2111587186042827/": {
      "reason": "AI_NOT_RELEVANT",
      "timestamp": "2025-08-29T22:34:39.985534"
    },
    "https://www.facebook.com/groups/1075915486829306/posts/1422070372213814/": {
      "reason": "AI_NOT_RELEVANT",
      "timestamp": "2025-08-30T01:55:24.749812"
    },
    "https://www.facebook.com/groups/1075915486829306/posts/1422025255551659/": {
      "reason": "AI_NOT_RELEVANT",
      "timestamp": "2025-08-30T01:56:04.439376"
    },
    "https://www.facebook.com/groups/181439002455412/posts/1840182653247697/": {
      "reason": "AI_NOT_RELEVANT",
      "timestamp": "2025-08-30T01:57:23.692106"
    },
    "https://www.facebook.com/groups/181439002455412/posts/1840179726581323/": {
      "reason": "AI_NOT_RELEVANT",
      "timestamp": "2025-08-30T01:57:23.693231"
    },
    "https://www.facebook.com/groups/478152972719598/posts/2111682386033307/": {
      "reason": "AI_NOT_RELEVANT",
      "timestamp": "2025-08-30T01:58:38.343352"
    },
    "https://www.facebook.com/groups/478152972719598/posts/2111664876035058/": {
      "reason": "AI_NOT_RELEVANT",
      "timestamp": "2025-08-30T01:58:38.344510"
    },
    "https://www.facebook.com/groups/478152972719598/posts/2111663802701832/": {
      "reason": "AI_NOT_RELEVANT",
      "timestamp": "2025-08-30T01:59:15.086115"
    },
    "https://www.facebook.com/groups/478152972719598/posts/2111653692702843/": {
      "reason": "AI_NOT_RELEVANT",
      "timestamp": "2025-08-30T01:59:15.087289"
    },
    "https://www.facebook.com/groups/478152972719598/posts/2111652896036256/": {
      "reason": "AI_NOT_RELEVANT",
      "timestamp": "2025-08-30T01:59:15.088733"
    },
    "https://www.facebook.com/groups/478152972719598/posts/2111753066026239/": {
      "reason": "AI_NOT_RELEVANT",
      "timestamp": "2025-08-30T03:39:48.235736"
    },
    "https://www.facebook.com/groups/1075915486829306/posts/1422107868876731/": {
      "reason": "AI_NOT_RELEVANT",
      "timestamp": "2025-08-30T04:29:48.638894"
    },
    "https://www.facebook.com/groups/181439002455412/posts/1840331539899475/": {
      "reason": "AI_NOT_RELEVANT",
      "timestamp": "2025-08-30T04:30:23.706251"
    },
    "https://www.facebook.com/groups/1075915486829306/posts/1422210592199792/": {
      "reason": "AI_NOT_RELEVANT",
      "timestamp": "2025-08-30T06:36:10.970356"
    },
    "https://www.facebook.com/groups/1075915486829306/posts/1422192032201648/": {
      "reason": "AI_NOT_RELEVANT",
      "timestamp": "2025-08-30T06:36:10.972965"
    },
    "https://www.facebook.com/groups/181439002455412/posts/1840353849897244/": {
      "reason": "AI_NOT_RELEVANT",
      "timestamp": "2025-08-30T06:36:48.511358"
    },
    "https://www.facebook.com/groups/478152972719598/posts/2111835062684706/": {
      "reason": "AI_NOT_RELEVANT",
      "timestamp": "2025-08-30T06:38:06.043413"
    },
    "https://www.facebook.com/groups/181439002455412/posts/1840398966559399/": {
      "reason": "AI_NOT_RELEVANT",
      "timestamp": "2025-08-30T07:24:09.751181"
    },
    "https://www.facebook.com/groups/1075915486829306/posts/1422284048859113/": {
      "reason": "AI_NOT_RELEVANT",
      "timestamp": "2025-08-30T08:35:09.016499"
    },
    "https://www.facebook.com/groups/1075915486829306/posts/1422271492193702/": {
      "reason": "AI_NOT_RELEVANT",
      "timestamp": "2025-08-30T08:35:09.017678"
    },
    "https://www.facebook.com/groups/1075915486829306/posts/1422258365528348/": {
      "reason": "AI_NOT_RELEVANT",
      "timestamp": "2025-08-30T08:35:09.018884"
    },
    "https://www.facebook.com/groups/181439002455412/posts/1840450983220864/": {
      "reason": "AI_NOT_RELEVANT",
      "timestamp": "2025-08-30T08:35:47.732742"
    },
    "https://www.facebook.com/groups/181439002455412/posts/1840437323222230/": {
      "reason": "AI_NOT_RELEVANT",
      "timestamp": "2025-08-30T08:35:47.733933"
    },
    "https://www.facebook.com/groups/478152972719598/posts/2111938972674315/": {
      "reason": "AI_NOT_RELEVANT",
      "timestamp": "2025-08-30T08:37:00.232147"
    },
    "https://www.facebook.com/groups/478152972719598/posts/2111967322671480/": {
      "reason": "AI_NOT_RELEVANT",
      "timestamp": "2025-08-30T09:35:34.461318"
    },
    "https://www.facebook.com/groups/478152972719598/posts/2111958029339076/": {
      "reason": "AI_NOT_RELEVANT",
      "timestamp": "2025-08-30T09:36:14.763126"
    },
    "https://www.facebook.com/groups/1075915486829306/posts/1422324288855089/": {
      "reason": "AI_NOT_RELEVANT",
      "timestamp": "2025-08-30T10:32:22.404827"
    },
    "https://www.facebook.com/groups/181439002455412/posts/1840516919880937/": {
      "reason": "AI_NOT_RELEVANT",
      "timestamp": "2025-08-30T10:32:59.092916"
    },
    "https://www.facebook.com/groups/181439002455412/posts/1840499706549325/": {
      "reason": "AI_NOT_RELEVANT",
      "timestamp": "2025-08-30T10:32:59.094409"
    },
    "https://www.facebook.com/groups/I6680/posts/24215071144828584/": {
      "reason": "AI_NOT_RELEVANT",
      "timestamp": "2025-08-30T10:34:10.595678"
    },
    "https://www.facebook.com/groups/478152972719598/posts/2112010679333811/": {
      "reason": "AI_NOT_RELEVANT",
      "timestamp": "2025-08-30T11:32:48.220971"
    },
    "https://www.facebook.com/groups/1075915486829306/posts/1422380422182809/": {
      "reason": "AI_NOT_RELEVANT",
      "timestamp": "2025-08-30T12:56:35.330151"
    },
    "https://www.facebook.com/groups/1075915486829306/posts/1422375322183319/": {
      "reason": "AI_NOT_RELEVANT",
      "timestamp": "2025-08-30T12:56:35.331338"
    },
    "https://www.facebook.com/groups/1075915486829306/posts/1422368242184027/": {
      "reason": "AI_NOT_RELEVANT",
      "timestamp": "2025-08-30T12:56:35.332826"
    },
    "https://www.facebook.com/groups/181439002455412/posts/1840565133209449/": {
      "reason": "AI_NOT_RELEVANT",
      "timestamp": "2025-08-30T12:57:43.804744"
    },
    "https://www.facebook.com/groups/478152972719598/posts/2112048892663323/": {
      "reason": "AI_NOT_RELEVANT",
      "timestamp": "2025-08-30T12:58:56.395513"
    },
    "https://www.facebook.com/groups/478152972719598/posts/2112032315998314/": {
      "reason": "AI_NOT_RELEVANT",
      "timestamp": "2025-08-30T12:58:56.397427"
    },
    "https://www.facebook.com/groups/I6680/posts/24222986144037084/": {
      "reason": "AI_NOT_RELEVANT",
      "timestamp": "2025-08-30T13:34:40.872582"
    },
    "https://www.facebook.com/groups/181439002455412/posts/1840658459866783/": {
      "reason": "AI_NOT_RELEVANT",
      "timestamp": "2025-08-30T14:29:06.178374"
    },
    "https://www.facebook.com/groups/181439002455412/posts/1840658053200157/": {
      "reason": "AI_NOT_RELEVANT",
      "timestamp": "2025-08-30T14:29:06.179471"
    },
    "https://www.facebook.com/groups/181439002455412/posts/1840643476534948/": {
      "reason": "AI_NOT_RELEVANT",
      "timestamp": "2025-08-30T14:29:06.180585"
    },
    "https://www.facebook.com/groups/478152972719598/posts/2112072955994250/": {
      "reason": "AI_NOT_RELEVANT",
      "timestamp": "2025-08-30T14:30:50.367282"
    },
    "https://www.facebook.com/groups/478152972719598/posts/2112012859333593/": {
      "reason": "AI_NOT_RELEVANT",
      "timestamp": "2025-08-30T14:30:50.368383"
    },
    "https://www.facebook.com/groups/1075915486829306/posts/1422339615520223/": {
      "reason": "AI_NOT_RELEVANT",
      "timestamp": "2025-08-30T15:33:41.586685"
    },
    "https://www.facebook.com/groups/181439002455412/posts/1840709153195047/": {
      "reason": "AI_NOT_RELEVANT",
      "timestamp": "2025-08-30T15:34:17.991793"
    },
    "https://www.facebook.com/groups/181439002455412/posts/1840706556528640/": {
      "reason": "AI_NOT_RELEVANT",
      "timestamp": "2025-08-30T15:34:17.992986"
    },
    "https://www.facebook.com/groups/181439002455412/posts/1840617279870901/": {
      "reason": "AI_NOT_RELEVANT",
      "timestamp": "2025-08-30T15:34:17.994685"
    },
    "https://www.facebook.com/groups/1075915486829306/posts/1422550745499110/": {
      "reason": "AI_NOT_RELEVANT",
      "timestamp": "2025-08-30T16:37:32.719380"
    },
    "https://www.facebook.com/groups/1075915486829306/posts/1422515662169285/": {
      "reason": "AI_NOT_RELEVANT",
      "timestamp": "2025-08-30T16:38:17.531926"
    },
    "https://www.facebook.com/groups/1075915486829306/posts/1422441975509987/": {
      "reason": "AI_NOT_RELEVANT",
      "timestamp": "2025-08-30T16:38:17.532935"
    },
    "https://www.facebook.com/groups/181439002455412/posts/1840739123192050/": {
      "reason": "AI_NOT_RELEVANT",
      "timestamp": "2025-08-30T16:38:55.496755"
    },
    "https://www.facebook.com/groups/181439002455412/posts/1840736856525610/": {
      "reason": "AI_NOT_RELEVANT",
      "timestamp": "2025-08-30T16:38:55.497783"
    },
    "https://www.facebook.com/groups/181439002455412/posts/1840731829859446/": {
      "reason": "AI_NOT_RELEVANT",
      "timestamp": "2025-08-30T16:39:40.457219"
    },
    "https://www.facebook.com/groups/I6680/posts/24223882770614088/": {
      "reason": "AI_NOT_RELEVANT",
      "timestamp": "2025-08-30T16:40:22.840378"
    },
    "https://www.facebook.com/groups/478152972719598/posts/2112175285984017/": {
      "reason": "AI_NOT_RELEVANT",
      "timestamp": "2025-08-30T16:41:41.338212"
    }
  },
  "total_rejected_count": 234,
  "timestamp": "2025-08-30T16:37:26.569013"
}